odoo8_addon_hr_expense_product_policy-8.0.1.0.0.99.dev11-py2.7-nspkg.pth
odoo8_addon_hr_expense_product_policy-8.0.1.0.0.99.dev11.dist-info/DESCRIPTION.rst
odoo8_addon_hr_expense_product_policy-8.0.1.0.0.99.dev11.dist-info/METADATA
odoo8_addon_hr_expense_product_policy-8.0.1.0.0.99.dev11.dist-info/RECORD
odoo8_addon_hr_expense_product_policy-8.0.1.0.0.99.dev11.dist-info/WHEEL
odoo8_addon_hr_expense_product_policy-8.0.1.0.0.99.dev11.dist-info/metadata.json
odoo8_addon_hr_expense_product_policy-8.0.1.0.0.99.dev11.dist-info/namespace_packages.txt
odoo8_addon_hr_expense_product_policy-8.0.1.0.0.99.dev11.dist-info/top_level.txt
odoo_addons/hr_expense_product_policy/README.rst
odoo_addons/hr_expense_product_policy/__init__.py
odoo_addons/hr_expense_product_policy/__openerp__.py
odoo_addons/hr_expense_product_policy/i18n/ar.po
odoo_addons/hr_expense_product_policy/i18n/de.po
odoo_addons/hr_expense_product_policy/i18n/es.po
odoo_addons/hr_expense_product_policy/i18n/fi.po
odoo_addons/hr_expense_product_policy/i18n/fr.po
odoo_addons/hr_expense_product_policy/i18n/hr_expense_product_policy.pot
odoo_addons/hr_expense_product_policy/i18n/it.po
odoo_addons/hr_expense_product_policy/i18n/nl.po
odoo_addons/hr_expense_product_policy/i18n/nl_NL.po
odoo_addons/hr_expense_product_policy/i18n/pt_BR.po
odoo_addons/hr_expense_product_policy/i18n/ro.po
odoo_addons/hr_expense_product_policy/i18n/sl.po
odoo_addons/hr_expense_product_policy/models/__init__.py
odoo_addons/hr_expense_product_policy/models/hr_department.py
odoo_addons/hr_expense_product_policy/models/hr_employee.py
odoo_addons/hr_expense_product_policy/models/hr_expense.py
odoo_addons/hr_expense_product_policy/models/hr_job.py
odoo_addons/hr_expense_product_policy/static/description/icon.png
odoo_addons/hr_expense_product_policy/tests/__init__.py
odoo_addons/hr_expense_product_policy/tests/test_hr_expense.py
odoo_addons/hr_expense_product_policy/views/hr_employee_views.xml
odoo_addons/hr_expense_product_policy/views/hr_expense_views.xml
